tiny_url/Get.py
tiny_url/Tiny.py
tiny_url/__init__.py
Tiny_URL-1.0.1.dist-info/LICENSE
Tiny_URL-1.0.1.dist-info/METADATA
Tiny_URL-1.0.1.dist-info/WHEEL
Tiny_URL-1.0.1.dist-info/top_level.txt
Tiny_URL-1.0.1.dist-info/RECORD
